hf_hub_lightning/__init__.py
hf_hub_lightning/callback.py
hf_hub_lightning-0.0.2.dist-info/LICENSE
hf_hub_lightning-0.0.2.dist-info/METADATA
hf_hub_lightning-0.0.2.dist-info/WHEEL
hf_hub_lightning-0.0.2.dist-info/top_level.txt
hf_hub_lightning-0.0.2.dist-info/RECORD
